CharStripper/__init__.py
CharStripper/core.py
CharStripper-0.1.2.dist-info/LICENSE.md
CharStripper-0.1.2.dist-info/METADATA
CharStripper-0.1.2.dist-info/WHEEL
CharStripper-0.1.2.dist-info/top_level.txt
CharStripper-0.1.2.dist-info/RECORD
