Metadata-Version: 2.1
Name: CharStripper
Version: 0.1.2
Summary: For replacing multiple characters in a text
Home-page: https://github.com/yagiziskirik/CharStripper
Author: Yagiz Iskirik
Author-email: yagiziskirik@icloud.com
Classifier: Programming Language :: Python :: 3
Classifier: License :: OSI Approved :: MIT License
Classifier: Operating System :: OS Independent
Requires-Python: >=3.7
License-File: LICENSE.md
